rickylim/__init__.py
rickylim/rickylim.py
rickylim-0.1.0.dist-info/AUTHORS.rst
rickylim-0.1.0.dist-info/LICENSE
rickylim-0.1.0.dist-info/METADATA
rickylim-0.1.0.dist-info/WHEEL
rickylim-0.1.0.dist-info/top_level.txt
rickylim-0.1.0.dist-info/RECORD
