Metadata-Version: 2.1
Name: rickylim
Version: 0.1.0
Summary: Hi, I am Ricky Lim!
Home-page: https://github.com/ricky-lim/rickylim
Author: Ricky Lim
Author-email: rickylim@tuta.io
License: GNU General Public License v3
Keywords: rickylim
Platform: UNKNOWN
Classifier: Development Status :: 2 - Pre-Alpha
Classifier: Intended Audience :: Developers
Classifier: License :: OSI Approved :: GNU General Public License v3 (GPLv3)
Classifier: Natural Language :: English
Classifier: Programming Language :: Python :: 3
Classifier: Programming Language :: Python :: 3.5
Classifier: Programming Language :: Python :: 3.6
Classifier: Programming Language :: Python :: 3.7
Classifier: Programming Language :: Python :: 3.8
Requires-Python: >=3.5
